<?xml version="1.0"?>
<QuizOnline>
    <!-- Reports -->
		<reports>
		<report questionID=" quizID="01" userID="01">
			<result>8</result>
		</report>
		<report reportID="02" quizID="01" userID="12">
			<result>9</result>
		</report>
		<report reportID="03" quizID="01" userID="10">
			<result>4</result>
		</report>
		<report reportID="04" quizID="01" userID="09">
			<result>9</result>
		</report>
		<report reportID="05" quizID="02" userID="02">
			<result>10</result>
		</report>
		<report reportID="06" quizID="02" userID="03">
			<result>9</result>
		</report>
		<report reportID="07" quizID="02" userID="04">
			<result>9</result>
		</report>
		<report reportID="08" quizID="03" userID="05">
			<result>4</result>
		</report>
		<report reportID="09" quizID="03" userID="06">
			<result>6</result>
		</report>
		<report reportID="10" quizID="04" userID="07">
			<result>10</result>
		</report>
		<report reportID="11" quizID="04" userID="12">
			<result>10</result>
		</report>
		<report reportID="12" quizID="05" userID="14">
			<result>6</result>
		</report>
		<report reportID="13" quizID="05" userID="16">
			<result>4</result>
		</report>
		<report reportID="14" quizID="05" userID="17">
			<result>8</result>
		</report>
		<report reportID="15" quizID="05" userID="18">
			<result>6</result>
		</report>
		<report reportID="16" quizID="06" userID="20">
			<result>9</result>
		</report>
		<report reportID="17" quizID="06" userID="07">
			<result>8</result>
		</report>
		<report reportID="18" quizID="06" userID="08">
			<result>4</result>
		</report>
		<report reportID="19" quizID="07" userID="13">
			<result>4</result>
		</report>
		<report reportID="20" quizID="07" userID="14">
			<result>6</result>
		</report>
		<report reportID="21" quizID="07" userID="17">
			<result>10</result>
		</report>
		<report reportID="22" quizID="08" userID="03">
			<result>9</result>
		</report>
		<report reportID="23" quizID="08" userID="04">
			<result>5</result>
		</report>
		<report reportID="24" quizID="08" userID="05">
			<result>8</result>
		</report>
		<report reportID="25" quizID="08" userID="11">
			<result>6</result>
		</report>
		<report reportID="26" quizID="09" userID="10">
			<result>6</result>
		</report>
		<report reportID="27" quizID="09" userID="12">
			<result>9</result>
		</report>
		<report reportID="28" quizID="09" userID="02">
			<result>5</result>
		</report>
		<report reportID="29" quizID="09" userID="01">
			<result>10</result>
		</report>
		<report reportID="30" quizID="10" userID="04">
			<result>7</result>
		</report>
		<report reportID="31" quizID="11" userID="05">
			<result>4</result>
		</report>
		<report reportID="32" quizID="11" userID="06">
			<result>9</result>
		</report>
		<report reportID="33" quizID="12" userID="08">
			<result>7</result>
		</report>
		<report reportID="34" quizID="12" userID="09">
			<result>4</result>
		</report>
		<report reportID="35" quizID="13" userID="11">
			<result>10</result>
		</report>
		<report reportID="36" quizID="13" userID="14">
			<result>5</result>
		</report>
		<report reportID="37" quizID="14" userID="18">
			<result>8</result>
		</report>
		<report reportID="38" quizID="14" userID="19">
			<result>10</result>
		</report>
		<report reportID="39" quizID="14" userID="20">
			<result>4</result>
		</report>
		<report reportID="40" quizID="14" userID="01">
			<result>7</result>
		</report>
    </reports>
</QuizOnline>
